README.rst
setup.py
torndb.py
torndb3.egg-info/PKG-INFO
torndb3.egg-info/SOURCES.txt
torndb3.egg-info/dependency_links.txt
torndb3.egg-info/requires.txt
torndb3.egg-info/top_level.txt