Metadata-Version: 1.0
Name: torndb3
Version: 0.4.5
Summary: A lightweight wrapper around MySQLdb.  Originally part of the Tornado framework.
Home-page: https://github.com/bdarnell/torndb
Author: Facebook
Author-email: python-tornado@googlegroups.com
License: http://www.apache.org/licenses/LICENSE-2.0
Platform: UNKNOWN
